MANIFEST.in
README
setup.py
src/jNlp/__init__.py
src/jNlp/edict_examples.py
src/jNlp/edict_examples.py~
src/jNlp/edict_search.py
src/jNlp/jCabocha.py
src/jNlp/jConvert.py
src/jNlp/jProcessing.py
src/jNlp/jTokenize.py
src/jNlp/data/__init__.py
src/jNlp/data/hiraganaChart.txt
src/jNlp/data/katakanaChart.txt
src/jNlp/jnlp/art.jpeg
src/jNlp/jnlp/index.html
src/jNlp/jnlp/index.rst
src/jNlp/jnlp/zope.css
src/jProcessing.egg-info/PKG-INFO
src/jProcessing.egg-info/SOURCES.txt
src/jProcessing.egg-info/dependency_links.txt
src/jProcessing.egg-info/top_level.txt