Metadata-Version: 1.0
Name: jProcessing
Version: 0.1
Summary: Japanese NLP Utilities
Home-page: http://www.jaist.ac.jp/~s1010205
Author: KATHURIA Pulkit
Author-email: pulkit@jaist.ac.jp
License: LICENSE.txt
Platform: UNKNOWN
Classifier: Development Status :: 2 - Pre-Alpha
Classifier: Natural Language :: Japanese
Classifier: Topic :: Scientific/Engineering :: Artificial Intelligence
Classifier: Programming Language :: Python :: 2.6
